[
  {
    "id": 1,
    "cursoId": 2,
    "nombre": "Sistema de Gestión Académica",
    "descripcion": "Desarrollo de un sistema web para gestión de estudiantes, cursos y calificaciones",
    "fechaInicio": "2024-02-01T00:00:00.000Z",
    "fechaFinalizacion": "2024-06-15T00:00:00.000Z",
    "estado": "En Progreso",
    "fechaAsignacion": "2024-01-15T00:00:00.000Z"
  },
  {
    "id": 2,
    "cursoId": 4,
    "nombre": "Implementación de Árbol Binario de Búsqueda",
    "descripcion": "Crear una biblioteca en Java para manejo de estructuras de datos tipo árbol",
    "fechaInicio": "2024-03-01T00:00:00.000Z",
    "fechaFinalizacion": "2024-05-30T00:00:00.000Z",
    "estado": "Completado",
    "fechaAsignacion": "2024-02-20T00:00:00.000Z"
  },
  {
    "id": 3,
    "cursoId": 5,
    "nombre": "Base de Datos para E-commerce",
    "descripcion": "Diseño e implementación de una base de datos relacional para tienda en línea",
    "fechaInicio": "2024-04-01T00:00:00.000Z",
    "fechaFinalizacion": "2024-07-15T00:00:00.000Z",
    "estado": "En Progreso",
    "fechaAsignacion": "2024-03-25T00:00:00.000Z"
  },
  {
    "id": 4,
    "cursoId": 8,
    "nombre": "Análisis de Mercado Digital",
    "descripcion": "Estudio económico del impacto de las redes sociales en el comercio local",
    "fechaInicio": "2024-02-15T00:00:00.000Z",
    "fechaFinalizacion": "2024-06-30T00:00:00.000Z",
    "estado": "En Progreso",
    "fechaAsignacion": "2024-02-01T00:00:00.000Z"
  },
  {
    "id": 5,
    "cursoId": 7,
    "nombre": "Documentación Histórica Digital",
    "descripcion": "Digitalización y catalogación de documentos históricos de El Salvador",
    "fechaInicio": "2024-01-10T00:00:00.000Z",
    "fechaFinalizacion": "2024-08-10T00:00:00.000Z",
    "estado": "En Progreso",
    "fechaAsignacion": "2023-12-20T00:00:00.000Z"
  }
]